sweetrpg_db/__init__.py
sweetrpg_db/exceptions.py
sweetrpg_db/utils.py
sweetrpg_db/mongodb/__init__.py
sweetrpg_db/mongodb/options.py
sweetrpg_db/mongodb/repo.py
sweetrpg_db/schema/__init__.py
sweetrpg_db-0.0.145.dist-info/LICENSE
sweetrpg_db-0.0.145.dist-info/METADATA
sweetrpg_db-0.0.145.dist-info/WHEEL
sweetrpg_db-0.0.145.dist-info/entry_points.txt
sweetrpg_db-0.0.145.dist-info/top_level.txt
sweetrpg_db-0.0.145.dist-info/RECORD
