Metadata-Version: 2.1
Name: sweetrpg-db
Version: 0.0.145
Home-page: https://sweetrpg.com
Author: Paul Schifferer
Author-email: dm@sweetrpg.com
License: MIT
Project-URL: Documentation, https://sweetrpg.github.io/db
Classifier: Development Status :: 3 - Alpha
Classifier: Environment :: Web Environment
Classifier: Framework :: Flask
Classifier: Intended Audience :: Developers
Classifier: License :: OSI Approved :: MIT License
Classifier: Operating System :: OS Independent
Classifier: Programming Language :: Python
Classifier: Topic :: Software Development :: Libraries :: Application Frameworks
License-File: LICENSE
Requires-Dist: dnspython~=2.0
Requires-Dist: marshmallow~=3.0
Requires-Dist: mongoengine~=0.27
Requires-Dist: PyMongo[srv]~=3.0
Requires-Dist: sweetrpg-model-core
